{"status":0,"data":{"tree":{"hasPower":1,"root_index":0,"spid":null,"seceret_key":null,"brand":2472,"entrys":3,"nodes":[{"children_index":[1,2,3],"frequency":0,"level":0,"parent_index":-1,"index":0},{"ir_zip_key":"GQY0O47qWSk68PmPNyz4MMsH6JN16eS+MqBiQF8Ms2UmZnlODRqopj7vXj2cPxYefow\/5ynnna6XV05RPCxjIiyXAfEHof6cbM4bSmeXE+AKIiEkvVxN2alaJTgiuepU","keysetids":["xm_1_4622"],"children_index":[],"frequency":37910,"level":1,"parent_index":0,"index":1,"keyid":"power"},{"ir_zip_key":"BaQscEX2nr2EvQETQoS35Bj0hnyL\/izk93VH0tMezL0RyXiYdyolkPHD0B44RlzzuU6OxQZNOBIhz+OLTSCEVm4mkynbh81mAf0y\/4jKzY55Bw68ttG0YSvcjYaCpEEQ","keysetids":["xm_1_2961"],"children_index":[],"frequency":38095,"level":1,"parent_index":0,"index":2,"keyid":"power"},{"ir_zip_key":"ejT8sLuIc04J4iRI06C7yRV9RNuXGgltlrPjrxa\/D7EuM4kxnuPrGOigncZgqhXx\/4ur1Hkahq8h9srfWSb8TAtuxB277dW4iJUxRNO0qUQ=","keysetids":["xm_1_4661"],"children_index":[],"frequency":38010,"level":1,"parent_index":0,"index":3,"keyid":"power"}],"status":true,"device":1,"version":1,"country":"IN"},"others":[]},"encoding":"UTF-8","language":"ZH_CN"}