{"status":0,"data":{"tree":{"hasPower":1,"root_index":0,"spid":null,"seceret_key":null,"brand":2518,"entrys":1,"nodes":[{"children_index":[1],"frequency":0,"level":0,"parent_index":-1,"index":0},{"ir_zip_key":"AUqKko9\/5Ab0hblpnfgP1Bj0hnyL\/izk93VH0tMezL0dnBvqtGWuljqT3yx6Q+Y3Yk4OEd3yGRhwJvQHopo0\/lBn4IAXzNFkLriLs\/sVseb3nhYzJ4k5PwHi+67\/PdrF","keysetids":["xm_1_3313"],"children_index":[],"frequency":38095,"level":1,"parent_index":0,"index":1,"keyid":"power"}],"status":true,"device":1,"version":1,"country":"IN"},"others":[]},"encoding":"UTF-8","language":"ZH_CN"}