{"status":0,"data":{"tree":{"hasPower":1,"root_index":0,"spid":null,"seceret_key":null,"brand":2319,"entrys":1,"nodes":[{"children_index":[1],"frequency":0,"level":0,"parent_index":-1,"index":0},{"ir_zip_key":"kLDae4w2PMEAiVkksZRIA80QFa9XToJST0+7kA6fjsoTbl7IFKJ2YGxHyIdJdRYNG2Js4wzNIl29AMQ6IO70b5fa6WcTLYx\/vW0vQskpkmN83ziJ45PuklnR0i6+qz3mN\/2UtFqU6yVdMs5CiAG8Dw==","keysetids":["xm_1_2777"],"children_index":[],"frequency":38180,"level":1,"parent_index":0,"index":1,"keyid":"power"}],"status":true,"device":1,"version":1,"country":"CN"},"others":[]},"encoding":"UTF-8","language":"ZH_CN"}