{"status":0,"data":{"tree":{},"others":[{"_id":"kk_1_2600_2709","key":{"vol+":"sJMK37x3mCZ193TaIgJNix27xfW\/IdWHgYTpRIHaM3qXScVihl2byUXTgEmUHaTweIXeyvruy4MelkwIVWrf0g==","tv_av":"sJMK37x3mCZ193TaIgJNi2AbaT0QXD7nNX55Vmn5vBADpj+zrnjRF4whad1QyorSJBmgTA0iWTIjXh88NusjpQ==","power":"sJMK37x3mCZ193TaIgJNi\/2i7ehW6Ukg6DhEX6pxmJH9uBxlVz7fHZO+7DfgdWuy82vfyv\/2MI3gF3AID5xxJg=="},"frequency":30000,"seceret_key":null,"source":"kk","kk_id":"2709","brand":"2600","match_counts":{"ID":2,"IR":5,"QA":1,"IQ":1,"UZ":1,"IN":2701,"MA":1,"AD":1,"CN":0,"RU":3,"US":2,"TM":2,"TJ":2,"PK":1,"AZ":1,"MY":1,"BD":2,"EG":1,"MM":1,"DZ":2,"KG":1,"UA":3},"locales":{"MY":2,"ID":2,"IN":2},"order":2,"device":1}]},"encoding":"UTF-8","language":"ZH_CN"}