{"status":0,"data":{"tree":{"hasPower":1,"root_index":0,"spid":null,"seceret_key":null,"brand":2288,"entrys":2,"nodes":[{"children_index":[1,2],"frequency":0,"level":0,"parent_index":-1,"index":0},{"ir_zip_key":"cpCKqRzt7cZC5bJmyhM6nssnGnwT2nDRHSw1BfALOogFdCFhYB3HByaD\/6GkTmHuuGCel1LSr\/bq463aLR7ASVH1br4Wnj+7UwEVU1+LwOJWuuOVWhV7xAVcoQkdTL66","keysetids":["xm_4_823"],"children_index":[],"frequency":38000,"level":1,"parent_index":0,"index":1,"keyid":"power"},{"ir_zip_key":"qgPnoUlMFJKaCzouUjPosNeyFVWR7hdS6SGcakoP9FEZDLOEs1nJIcraNuWFdP29oLhcoU8xZKzdd8gjgQK+J9SR\/IphvTXwDk6nxbtnQZAIw8d9sEiBGz7pYasC\/AqmVrrjlVoVe8QFXKEJHUy+ug==","keysetids":["xm_4_811"],"children_index":[],"frequency":38180,"level":1,"parent_index":0,"index":2,"keyid":"power"}],"status":true,"device":4,"version":1,"country":"CN"},"others":[]},"encoding":"UTF-8","language":"ZH_CN"}