{"status":0,"data":{"tree":{"hasPower":1,"root_index":0,"spid":null,"seceret_key":null,"brand":1770,"entrys":2,"nodes":[{"children_index":[1,2],"frequency":0,"level":0,"parent_index":-1,"index":0},{"ir_zip_key":"CBj0qIehhGHcs9YJOOs07g4gQIhaVvMWI9h1TpYpm7QiY7kBlTwtUOPW6qF7\/ctWUrKXyNkjh1vsnFZfxVWEMVgJ1D8nifJNPpSsHkmj0ZqmDyWe1qlg\/dF5iTldlxGrbYx\/flYeSsvJJj0\/6ZIOVMQYgz78d13gNSNrlGXBM7s=","keysetids":["xm_4_1348"],"children_index":[],"frequency":38000,"level":1,"parent_index":0,"index":1,"keyid":"power"},{"ir_zip_key":"X2TISSZeJcWQps1QpzvkrxNK8iUDwoTpdMSkG40YNAwFKnH8YKqVAw4lolNv3LCXDfBFUtVDMbtE0gksD32EC2Rm+lGvxydfHI22n9mxz\/MpAcvGa\/Ns+i5qX4orHRBJUN2mppaArMy1lbvq6FBftA==","keysetids":["xm_4_1349"],"children_index":[],"frequency":38000,"level":1,"parent_index":0,"index":2,"keyid":"power"}],"status":true,"device":4,"version":1,"country":"CN"},"others":[]},"encoding":"UTF-8","language":"ZH_CN"}